[{"completion_status":"under_development",		"created_at":null,		"current_speed":50.0,		"description":null,		"flags":1,		"id":null,		"name_unique":"multivib-bi.txt",		"power_range":50.0,		"sim_speed":10.391409633455755,		"time_step":5.0e-06,		"title":"Bistable Multivib (Flip-Flop)",		"topic":"Multivibrators",		"updated_at":null,		"voltage_range":5.0},		
{"sym":"r",		"x1":"144",		"y1":"32",		"x2":"144",		"y2":"128",		"flags":"0",		"params":["100.0"]},		
{"sym":"r",		"x1":"384",		"y1":"32",		"x2":"384",		"y2":"128",		"flags":"0",		"params":["100.0"]},		
{"sym":"w",		"x1":"384",		"y1":"128",		"x2":"384",		"y2":"192",		"flags":"0",		"params":[]},		
{"sym":"t",		"x1":"304",		"y1":"208",		"x2":"384",		"y2":"208",		"flags":"0",		"params":["1",		"0.617227886429507",		"0.6759235619928714",		"100.0"]},		
{"sym":"w",		"x1":"224",		"y1":"128",		"x2":"304",		"y2":"208",		"flags":"0",		"params":[]},		
{"sym":"w",		"x1":"304",		"y1":"128",		"x2":"224",		"y2":"208",		"flags":"0",		"params":[]},		
{"sym":"t",		"x1":"224",		"y1":"208",		"x2":"144",		"y2":"208",		"flags":"0",		"params":["1",		"-4.584864481423058",		"0.029057265154527386",		"100.0"]},		
{"sym":"w",		"x1":"144",		"y1":"128",		"x2":"144",		"y2":"192",		"flags":"0",		"params":[]},		
{"sym":"r",		"x1":"304",		"y1":"128",		"x2":"384",		"y2":"128",		"flags":"0",		"params":["1020.0"]},		
{"sym":"r",		"x1":"144",		"y1":"128",		"x2":"224",		"y2":"128",		"flags":"0",		"params":["1020.0"]},		
{"sym":"M",		"x1":"384",		"y1":"128",		"x2":"448",		"y2":"128",		"flags":"0",		"params":["2.5"]},		
{"sym":"w",		"x1":"144",		"y1":"32",		"x2":"384",		"y2":"32",		"flags":"0",		"params":[]},		
{"sym":"M",		"x1":"144",		"y1":"128",		"x2":"80",		"y2":"128",		"flags":"0",		"params":["2.5"]},		
{"sym":"R",		"x1":"144",		"y1":"32",		"x2":"80",		"y2":"32",		"flags":"0",		"params":["0",		"40.0",		"5.0",		"0.0",		"0.0",		"0.5"]},		
{"sym":"r",		"x1":"224",		"y1":"208",		"x2":"224",		"y2":"304",		"flags":"0",		"params":["1000.0"]},		
{"sym":"r",		"x1":"304",		"y1":"208",		"x2":"304",		"y2":"304",		"flags":"0",		"params":["1000.0"]},		
{"sym":"L",		"x1":"224",		"y1":"304",		"x2":"80",		"y2":"304",		"flags":"0",		"params":["0",		"true",		"5.0",		"0.0"]},		
{"sym":"L",		"x1":"304",		"y1":"304",		"x2":"448",		"y2":"304",		"flags":"0",		"params":["0",		"true",		"5.0",		"0.0"]},		
{"sym":"x",		"x1":"54",		"y1":"105",		"x2":"106",		"y2":"109",		"flags":"2",		"params":["16",		"output"]},		
{"sym":"x",		"x1":"422",		"y1":"100",		"x2":"474",		"y2":"104",		"flags":"0",		"params":["16",		"output"]},		
{"sym":"x",		"x1":"70",		"y1":"278",		"x2":"93",		"y2":"282",		"flags":"0",		"params":["16",		"set"]},		
{"sym":"x",		"x1":"429",		"y1":"277",		"x2":"468",		"y2":"281",		"flags":"0",		"params":["16",		"reset"]},		
{"sym":"g",		"x1":"144",		"y1":"224",		"x2":"144",		"y2":"256",		"flags":"0",		"params":[]},		
{"sym":"g",		"x1":"384",		"y1":"224",		"x2":"384",		"y2":"256",		"flags":"0",		"params":[]},		
{"sym":"x",		"x1":"106",		"y1":"212",		"x2":"128",		"y2":"216",		"flags":"0",		"params":["16",		"Q1"]},		
{"sym":"x",		"x1":"400",		"y1":"213",		"x2":"422",		"y2":"217",		"flags":"0",		"params":["16",		"Q2"]}]