[{"completion_status":"complete",		"created_at":null,		"current_speed":48.0,		"description":null,		"flags":1,		"id":null,		"name_unique":"res-series.txt",		"power_range":0.0,		"sim_speed":15.0,		"time_step":5.0e-06,		"title":"Series Resonance",		"topic":"A/C Circuits",		"updated_at":null,		"voltage_range":5.0},		
{"sym":"v",		"x1":"80",		"y1":"112",		"x2":"80",		"y2":"32",		"flags":"0",		"params":["1",		"35.0",		"5.0",		"0.0"]},		
{"sym":"v",		"x1":"80",		"y1":"224",		"x2":"80",		"y2":"144",		"flags":"0",		"params":["1",		"41.09",		"5.0",		"0.0"]},		
{"sym":"v",		"x1":"80",		"y1":"336",		"x2":"80",		"y2":"256",		"flags":"0",		"params":["1",		"45.0",		"5.0",		"0.0"]},		
{"sym":"r",		"x1":"80",		"y1":"32",		"x2":"432",		"y2":"32",		"flags":"0",		"params":["10.0"]},		
{"sym":"c",		"x1":"432",		"y1":"32",		"x2":"432",		"y2":"112",		"flags":"0",		"params":["1.5E-5",		"0"]},		
{"sym":"l",		"x1":"80",		"y1":"112",		"x2":"432",		"y2":"112",		"flags":"0",		"params":["1.0",		"0"]},		
{"sym":"r",		"x1":"80",		"y1":"144",		"x2":"432",		"y2":"144",		"flags":"0",		"params":["10.0"]},		
{"sym":"c",		"x1":"432",		"y1":"144",		"x2":"432",		"y2":"224",		"flags":"0",		"params":["1.5E-5",		"0"]},		
{"sym":"l",		"x1":"80",		"y1":"224",		"x2":"432",		"y2":"224",		"flags":"0",		"params":["1.0",		"0"]},		
{"sym":"r",		"x1":"80",		"y1":"256",		"x2":"432",		"y2":"256",		"flags":"0",		"params":["10.0"]},		
{"sym":"c",		"x1":"432",		"y1":"256",		"x2":"432",		"y2":"336",		"flags":"0",		"params":["1.5E-5",		"0"]},		
{"sym":"l",		"x1":"80",		"y1":"336",		"x2":"432",		"y2":"336",		"flags":"0",		"params":["1.0",		"0"]},		
{"sym":"h",		"x1":"1",		"y1":"5",		"x2":"4",		"y2":null,		"flags":null,		"params":[]},		
{"sym":"o",		"x1":"4",		"y1":"64",		"x2":"0",		"y2":"3",		"flags":"20.0",		"params":["0.1"]},		
{"sym":"o",		"x1":"7",		"y1":"64",		"x2":"0",		"y2":"3",		"flags":"160.0",		"params":["0.8"]},		
{"sym":"o",		"x1":"10",		"y1":"64",		"x2":"0",		"y2":"3",		"flags":"40.0",		"params":["0.2"]}]