[{"completion_status":"complete",		"created_at":null,		"current_speed":63.0,		"description":null,		"flags":1,		"id":null,		"name_unique":"sawtooth.txt",		"power_range":50.0,		"sim_speed":10.634267539816555,		"time_step":5.0e-06,		"title":"Sawtooth Wave Generator",		"topic":"Oscillators",		"updated_at":null,		"voltage_range":5.0},		
{"sym":"a",		"x1":"160",		"y1":"224",		"x2":"272",		"y2":"224",		"flags":"0",		"params":["15.0",		"-15.0",		"1000000.0"]},		
{"sym":"w",		"x1":"160",		"y1":"240",		"x2":"160",		"y2":"304",		"flags":"0",		"params":[]},		
{"sym":"w",		"x1":"160",		"y1":"304",		"x2":"272",		"y2":"304",		"flags":"0",		"params":[]},		
{"sym":"r",		"x1":"272",		"y1":"224",		"x2":"272",		"y2":"304",		"flags":"0",		"params":["100000.0"]},		
{"sym":"a",		"x1":"384",		"y1":"240",		"x2":"496",		"y2":"240",		"flags":"0",		"params":["15.0",		"-15.0",		"1000000.0"]},		
{"sym":"r",		"x1":"272",		"y1":"304",		"x2":"352",		"y2":"304",		"flags":"0",		"params":["40000.0"]},		
{"sym":"w",		"x1":"352",		"y1":"304",		"x2":"496",		"y2":"304",		"flags":"0",		"params":[]},		
{"sym":"w",		"x1":"496",		"y1":"304",		"x2":"496",		"y2":"240",		"flags":"0",		"params":[]},		
{"sym":"w",		"x1":"496",		"y1":"240",		"x2":"496",		"y2":"176",		"flags":"0",		"params":[]},		
{"sym":"c",		"x1":"384",		"y1":"176",		"x2":"496",		"y2":"176",		"flags":"0",		"params":["5.0E-7",		"4.758165877822716"]},		
{"sym":"w",		"x1":"384",		"y1":"176",		"x2":"384",		"y2":"224",		"flags":"0",		"params":[]},		
{"sym":"g",		"x1":"384",		"y1":"256",		"x2":"384",		"y2":"272",		"flags":"0",		"params":[]},		
{"sym":"O",		"x1":"496",		"y1":"240",		"x2":"560",		"y2":"240",		"flags":"0",		"params":[]},		
{"sym":"w",		"x1":"160",		"y1":"208",		"x2":"128",		"y2":"208",		"flags":"0",		"params":[]},		
{"sym":"g",		"x1":"128",		"y1":"208",		"x2":"128",		"y2":"240",		"flags":"0",		"params":[]},		
{"sym":"r",		"x1":"384",		"y1":"176",		"x2":"320",		"y2":"176",		"flags":"0",		"params":["5000.0"]},		
{"sym":"r",		"x1":"384",		"y1":"224",		"x2":"320",		"y2":"224",		"flags":"0",		"params":["40000.0"]},		
{"sym":"d",		"x1":"272",		"y1":"176",		"x2":"320",		"y2":"176",		"flags":"1",		"params":["0.805904783"]},		
{"sym":"d",		"x1":"320",		"y1":"224",		"x2":"272",		"y2":"224",		"flags":"1",		"params":["0.805904783"]},		
{"sym":"w",		"x1":"272",		"y1":"176",		"x2":"272",		"y2":"224",		"flags":"0",		"params":[]},		
{"sym":"o",		"x1":"12",		"y1":"64",		"x2":"0",		"y2":"42",		"flags":"10.0",		"params":["9.765625E-5",		"0",		"-1"]}]